harmonix/__init__.py
harmonix/harmonix.py
harmonix/solution.py
harmonix/test_utils.py
harmonix/utils.py
harmonix-0.0.1.dist-info/LICENSE
harmonix-0.0.1.dist-info/METADATA
harmonix-0.0.1.dist-info/WHEEL
harmonix-0.0.1.dist-info/top_level.txt
harmonix-0.0.1.dist-info/RECORD
