Metadata-Version: 2.1
Name: harmonix
Version: 0.0.1
Summary: Analytic interferometry of stellar surfaces using spherical harmonics in Jax
Author-email: Shashank Dholakia <s.dholakia@uq.edu.au>
Project-URL: repository, https://github.com/shashankdholakia/harmonix/
Keywords: python,interferometry,machine-learning,jax,autodiff,differentiable,simulation,telescope
Classifier: Programming Language :: Python :: 3
Classifier: Operating System :: OS Independent
Requires-Python: >=3.8
License-File: LICENSE
Requires-Dist: jax
Requires-Dist: jaxlib
Requires-Dist: scipy
Requires-Dist: numpy
Requires-Dist: jaxoplanet >=0.0.2
Requires-Dist: zodiax >=0.4.1
Provides-Extra: dev
Requires-Dist: pytest ; extra == 'dev'
Requires-Dist: sympy ; extra == 'dev'
Provides-Extra: extras
Requires-Dist: matplotlib ; extra == 'extras'
Requires-Dist: jupyter ; extra == 'extras'
Requires-Dist: jupyterlab ; extra == 'extras'
Requires-Dist: tqdm ; extra == 'extras'
Requires-Dist: numpyro ; extra == 'extras'
